seismic_format/__init__.py
seismic_format/quakeml_to_y2k.py
seismic_format/seisan_to_quakeml.py
seismic_format/y2k_to_quakeml.py
seismic_format/formats/22-0106-00L.S202004.cols
seismic_format/formats/format.Y2000_header_archive
seismic_format/formats/format.Y2000_station_archive
seismic_format/formats/format.nordic.type1
seismic_format/formats/format.nordic.type4
seismic_format/formats/format.nordic.typeE
seismic_format/formats/format.nordic.typeH
seismic_format/libs/__init__.py
seismic_format/libs/cmd_line.py
seismic_format/libs/lib_y2k.py
seismic_format/libs/libs_log.py
seismic_format/libs/mappings.py
seismic_format/libs/nordic_to_qml.py
seismic_format/libs/qml_to_y2k.py
seismic_format/libs/y2k_to_qml.py
seismic_format-0.0.3.dist-info/AUTHORS.rst
seismic_format-0.0.3.dist-info/LICENSE
seismic_format-0.0.3.dist-info/METADATA
seismic_format-0.0.3.dist-info/WHEEL
seismic_format-0.0.3.dist-info/entry_points.txt
seismic_format-0.0.3.dist-info/top_level.txt
seismic_format-0.0.3.dist-info/RECORD
