Metadata-Version: 2.1
Name: seismic-format
Version: 0.0.3
Summary: Collection of tools for converting between different seismic formats
Home-page: https://gitlab.isti.com/mhagerty/seismic-format
Author: Mike Hagerty
Author-email: mhagerty@isti.com
License: MIT
Classifier: Development Status :: 2 - Pre-Alpha
Classifier: Intended Audience :: Developers
Classifier: License :: OSI Approved :: MIT License
Classifier: Natural Language :: English
Classifier: Programming Language :: Python :: 2
Classifier: Programming Language :: Python :: 2.7
Classifier: Programming Language :: Python :: 3
Classifier: Programming Language :: Python :: 3.3
Classifier: Programming Language :: Python :: 3.4
Classifier: Programming Language :: Python :: 3.5
License-File: LICENSE
License-File: AUTHORS.rst
Requires-Dist: click
Requires-Dist: obspy
Requires-Dist: pyyaml
Provides-Extra: cli
Requires-Dist: click ; extra == 'cli'
Provides-Extra: develop
Requires-Dist: tox ; extra == 'develop'
Requires-Dist: pytest ; extra == 'develop'
Requires-Dist: pytest-runner ; extra == 'develop'
Requires-Dist: click ; extra == 'develop'
